audiotame/acx.py
audiotame/app.py
audiotame/audiotame.py
audiotame/audiotame.sh
audiotame/main.py
audiotame/arnndn-models/.git
audiotame/arnndn-models/README.md
audiotame/arnndn-models/bd.rnnn
audiotame/arnndn-models/cb.rnnn
audiotame/arnndn-models/lq.rnnn
audiotame/arnndn-models/mp.rnnn
audiotame/arnndn-models/sh.rnnn
audiotame/arnndn-models/std.rnnn
audiotame-0.1.16.dist-info/licenses/LICENSE
audiotame-0.1.16.dist-info/METADATA
audiotame-0.1.16.dist-info/WHEEL
audiotame-0.1.16.dist-info/entry_points.txt
audiotame-0.1.16.dist-info/top_level.txt
audiotame-0.1.16.dist-info/RECORD
