Metadata-Version: 2.4
Name: audiotame
Version: 0.1.16
Summary: Command-line tool that normalizes audio and reduces noise.
Author: veralvx
Maintainer: veralvx
Project-URL: Homepage, https://github.com/veralvx/audiotame
Project-URL: Repository, https://github.com/veralvx/audiotame.git
Project-URL: Issues, https://github.com/veralvx/audiotame/issues
Project-URL: Mastodon, https://mastodon.social/@veralvx
Project-URL: Twitter, https://x.com/veralvx
Project-URL: Changelog, https://github.com/veralvx/audiotame/blob/main/CHANGELOG.md
Keywords: audio,normalization,noise reduction,normalize audio,acx,audio conversion
Classifier: Programming Language :: Python :: 3
Classifier: Programming Language :: Python :: 3.9
Classifier: Programming Language :: Python :: 3.10
Classifier: Programming Language :: Python :: 3.11
Classifier: Programming Language :: Python :: 3.12
Classifier: Programming Language :: Python :: 3.13
Classifier: Programming Language :: Python :: 3.14
Classifier: Programming Language :: Python
Classifier: Programming Language :: Unix Shell
Classifier: Environment :: Console
Classifier: Operating System :: Unix
Classifier: Operating System :: POSIX :: Linux
Classifier: Intended Audience :: Developers
Classifier: Intended Audience :: End Users/Desktop
Classifier: Topic :: Multimedia :: Sound/Audio
Classifier: Topic :: Multimedia :: Sound/Audio :: Analysis
Classifier: Topic :: Multimedia :: Sound/Audio :: Conversion
Classifier: License :: OSI Approved :: MIT License
Classifier: Natural Language :: English
Requires-Python: >=3.9
License-File: LICENSE
Requires-Dist: ffmpeg-normalize<2.0,>=1.31.0
Provides-Extra: gui
Requires-Dist: gradio<6.0,>=5.0; python_version >= "3.10" and extra == "gui"
Dynamic: license-file
